tests/__init__.py
tests/test_builders_default.py
tests/test_builders_simple.py
tests/test_builders_union_metrics.py
tests/test_notification.py
tests/test_report.py
tests/test_session.py
tests/test_storage_local.py
tests/test_subtask.py
tests/test_task.py
worker_analyzer/__init__.py
worker_analyzer/analyzer.py
worker_analyzer/builders.py
worker_analyzer/common.py
worker_analyzer/notification.py
worker_analyzer/report.py
worker_analyzer/storage.py
worker_analyzer-1.0.4.dist-info/LICENSE
worker_analyzer-1.0.4.dist-info/METADATA
worker_analyzer-1.0.4.dist-info/WHEEL
worker_analyzer-1.0.4.dist-info/top_level.txt
worker_analyzer-1.0.4.dist-info/RECORD
