Metadata-Version: 2.1
Name: worker-analyzer
Version: 1.0.4
Summary: Package for analyze and monitoring worker performance
Home-page: UNKNOWN
Author: Claudio Vinicius Oliveira
Author-email: claudio.datascience@gmail.com
License: UNKNOWN
Platform: UNKNOWN
License-File: LICENSE
Requires-Dist: numpy <1.26.2,>=1.19.5
Requires-Dist: pandas <2.1.3,>=1.1.5
Requires-Dist: python-dateutil ==2.8.2
Requires-Dist: pytz ==2023.3.post1
Requires-Dist: tzdata ==2023.3
